{
    "APPLICATION_THEME": "default",
    "appaddrkey": "",
    "appidkey": "CRE8",
    "appnamekey": "CRE8OR",
    "apppackagekey": "",
    "appversionkey": "1.0.0",
    "build": "debug",
    "category": "app",
    "createdVizVersion": "8.0.1",
    "createdgaversion": "8.0.1",
    "currentgaversion": "8.0.1",
    "enableCustomData": false,
    "isDpScaleFactor": true,
    "isMVC": true,
    "isNewAppWithRespectToAndroidPackageName": "",
    "konyVizVersion": "8.0.1",
    "mastersProperties": {
        "mastersVersion": "2.0.0"
    },
    "mwaddrkey": "",
    "mwhttpsportkey": "",
    "mwportkey": "",
    "project.type": "js",
    "project_version": "sprint29",
    "referenceWidth": "375",
    "startupformkey": "a22d8e8371d24e128edfce6d98dddfa3",
    "vendornamekey": "KonyLabs",
    "winmobileguidkey": "",
    "defaulttheme": "defaultTheme",
    "nativeContainerProperties": {
        "isModified": false,
        "isEnableJSContainer": false,
        "isEnableJSContainerAndroid": false,
        "isEnableJSContaineriOS": false
    },
    "appmenu": {
        "desktop": {
            "data": [
                {
                    "id": "appmenuitemid1",
                    "title": "Item 1",
                    "icon": {
                        "default": "option1.png"
                    },
                    "kuid": "jbb7e12d9572416dbef897cd5c245a27"
                },
                {
                    "id": "appmenuitemid2",
                    "title": "Item 2",
                    "icon": {
                        "default": "option2.png"
                    },
                    "kuid": "d281344ba38c40239c02e1d44fe58f0f"
                },
                {
                    "id": "appmenuitemid3",
                    "title": "Item 3",
                    "icon": {
                        "default": "option3.png"
                    },
                    "kuid": "a127783841d441b98b6afafc8b461b43"
                },
                {
                    "id": "appmenuitemid4",
                    "title": "Item 4",
                    "icon": {
                        "default": "option4.png"
                    },
                    "kuid": "a896116ae2eb4c9fa6d254d131ccca85"
                }
            ]
        },
        "focusSkin": "",
        "focusskin": "",
        "mobile": {
            "data": []
        },
        "osPlatform": "",
        "osVersion": "iOS7",
        "skin": "",
        "tablet": {
            "data": [
                {
                    "id": "appmenuitemid1",
                    "title": "Item 1",
                    "icon": {
                        "default": "option1.png"
                    },
                    "kuid": "e94ef160dd2d4a52866ba923640a8ba0",
                    "windows8": {
                        "position": "BOTTOM_LEFT",
                        "appBarButtonStyle": "No Style"
                    }
                },
                {
                    "id": "appmenuitemid2",
                    "title": "Item 2",
                    "icon": {
                        "default": "option2.png"
                    },
                    "kuid": "d454640dbaad4837968d11118c64e62b",
                    "windows8": {
                        "position": "BOTTOM_LEFT",
                        "appBarButtonStyle": "No Style"
                    }
                },
                {
                    "id": "appmenuitemid3",
                    "title": "Item 3",
                    "icon": {
                        "default": "option3.png"
                    },
                    "kuid": "c573fed7232c4174a584135d02705243",
                    "windows8": {
                        "position": "BOTTOM_LEFT",
                        "appBarButtonStyle": "No Style"
                    }
                },
                {
                    "id": "appmenuitemid4",
                    "title": "Item 4",
                    "icon": {
                        "default": "option4.png"
                    },
                    "kuid": "f7dc19888f174f5f8a04caea5cc5f251",
                    "windows8": {
                        "position": "BOTTOM_LEFT",
                        "appBarButtonStyle": "No Style"
                    }
                }
            ]
        },
        "wType": "Appmenu",
        "context": {
            "platform": "iphone",
            "channel": "mobile"
        }
    },
    "accountCloudGuid": "73148cbf-d5f9-4a76-b0f1-ad6766f95e3b",
    "projectCloudGuid": "d31d0b42-16de-4fa8-9134-583df013df4c",
    "prototype": {
        "createdOn": "2017-11-30T11:19:31.341Z",
        "createdById": "1230bf6e-15b1-45f8-9cf3-55d18a8e383d",
        "createdBy": "Barten Verschoor",
        "shareGuid": "VZXKN",
        "resourceId": "4cdc16ca-74f2-4e55-b8ef-ed75d7d1f26a",
        "PublishMode": "public"
    },
    "wap_ip_fontsize": "12",
    "wap_android240_fontsize": "10",
    "wap_android320_fontsize": "12",
    "wap_android360_fontsize": "13",
    "wap_android400_fontsize": "14",
    "wap_android440_fontsize": "15",
    "wap_android480_fontsize": "16",
    "wap_android640_fontsize": "19",
    "wap_spaipad_fontsize": "17",
    "wap_spaandroidtab_fontsize": "17",
    "wap_spaandroidtabldpi_fontsize": "17",
    "wap_spaandroidtabmdpi_fontsize": "14",
    "wap_spaandroidtabhdpi_fontsize": "16",
    "wap_spaandroidtabxhdpi_fontsize": "18",
    "wap_winphone320_fontsize": "12",
    "wap_winphone480_fontsize": "12",
    "wap_spawindowstab_fontsize": "17",
    "wap_bb240_fontsize": "12",
    "wap_bb320_fontsize": "15",
    "wap_bb360_fontsize": "13",
    "wap_bb400_fontsize": "14",
    "wap_bb440_fontsize": "15",
    "wap_bb480_fontsize": "17",
    "ipadlandscapemodekey": "portrait",
    "supportedorientations": [
        "portrait"
    ],
    "desktopwebbasefontsize": "16",
    "desktopwebwidthoption": "percentage",
    "desktopwebaligenmentoption": "Left"
}